[
  {
    "days_to_complete": 442,
    "daily_series_completed_rolling": 5394,
    "date": "03-20-2021"
  },
  {
    "days_to_complete": 413,
    "daily_series_completed_rolling": 5783,
    "date": "03-19-2021"
  },
  {
    "days_to_complete": 378,
    "daily_series_completed_rolling": 6343,
    "date": "03-18-2021"
  },
  {
    "days_to_complete": 355,
    "daily_series_completed_rolling": 6765,
    "date": "03-17-2021"
  },
  {
    "days_to_complete": 340,
    "daily_series_completed_rolling": 7076,
    "date": "03-16-2021"
  },
  {
    "days_to_complete": 335,
    "daily_series_completed_rolling": 7205,
    "date": "03-15-2021"
  },
  {
    "days_to_complete": 327,
    "daily_series_completed_rolling": 7398,
    "date": "03-14-2021"
  },
  {
    "days_to_complete": 324,
    "daily_series_completed_rolling": 7477,
    "date": "03-13-2021"
  },
  {
    "days_to_complete": 334,
    "daily_series_completed_rolling": 7286,
    "date": "03-12-2021"
  },
  {
    "days_to_complete": 352,
    "daily_series_completed_rolling": 6933,
    "date": "03-11-2021"
  },
  {
    "days_to_complete": 363,
    "daily_series_completed_rolling": 6750,
    "date": "03-10-2021"
  },
  {
    "days_to_complete": 354,
    "daily_series_completed_rolling": 6937,
    "date": "03-09-2021"
  },
  {
    "days_to_complete": 364,
    "daily_series_completed_rolling": 6777,
    "date": "03-08-2021"
  },
  {
    "days_to_complete": 373,
    "daily_series_completed_rolling": 6633,
    "date": "03-07-2021"
  },
  {
    "days_to_complete": 374,
    "daily_series_completed_rolling": 6624,
    "date": "03-06-2021"
  },
  {
    "days_to_complete": 384,
    "daily_series_completed_rolling": 6459,
    "date": "03-05-2021"
  },
  {
    "days_to_complete": 368,
    "daily_series_completed_rolling": 6762,
    "date": "03-04-2021"
  },
  {
    "days_to_complete": 355,
    "daily_series_completed_rolling": 7042,
    "date": "03-03-2021"
  },
  {
    "days_to_complete": 370,
    "daily_series_completed_rolling": 6781,
    "date": "03-02-2021"
  },
  {
    "days_to_complete": 372,
    "daily_series_completed_rolling": 6752,
    "date": "03-01-2021"
  },
  {
    "days_to_complete": 371,
    "daily_series_completed_rolling": 6785,
    "date": "02-28-2021"
  },
  {
    "days_to_complete": 378,
    "daily_series_completed_rolling": 6677,
    "date": "02-27-2021"
  },
  {
    "days_to_complete": 385,
    "daily_series_completed_rolling": 6569,
    "date": "02-26-2021"
  },
  {
    "days_to_complete": 405,
    "daily_series_completed_rolling": 6261,
    "date": "02-25-2021"
  },
  {
    "days_to_complete": 432,
    "daily_series_completed_rolling": 5891,
    "date": "02-24-2021"
  },
  {
    "days_to_complete": 447,
    "daily_series_completed_rolling": 5713,
    "date": "02-23-2021"
  },
  {
    "days_to_complete": 504,
    "daily_series_completed_rolling": 5085,
    "date": "02-22-2021"
  },
  {
    "days_to_complete": 556,
    "daily_series_completed_rolling": 4615,
    "date": "02-21-2021"
  },
  {
    "days_to_complete": 569,
    "daily_series_completed_rolling": 4517,
    "date": "02-20-2021"
  },
  {
    "days_to_complete": 580,
    "daily_series_completed_rolling": 4433,
    "date": "02-19-2021"
  },
  {
    "days_to_complete": 605,
    "daily_series_completed_rolling": 4269,
    "date": "02-18-2021"
  },
  {
    "days_to_complete": 597,
    "daily_series_completed_rolling": 4335,
    "date": "02-17-2021"
  },
  {
    "days_to_complete": 628,
    "daily_series_completed_rolling": 4132,
    "date": "02-16-2021"
  },
  {
    "days_to_complete": 611,
    "daily_series_completed_rolling": 4250,
    "date": "02-15-2021"
  },
  {
    "days_to_complete": 612,
    "daily_series_completed_rolling": 4245,
    "date": "02-14-2021"
  },
  {
    "days_to_complete": 619,
    "daily_series_completed_rolling": 4204,
    "date": "02-13-2021"
  },
  {
    "days_to_complete": 653,
    "daily_series_completed_rolling": 3987,
    "date": "02-12-2021"
  },
  {
    "days_to_complete": 725,
    "daily_series_completed_rolling": 3599,
    "date": "02-11-2021"
  },
  {
    "days_to_complete": 910,
    "daily_series_completed_rolling": 2878,
    "date": "02-10-2021"
  },
  {
    "days_to_complete": 1013,
    "daily_series_completed_rolling": 2591,
    "date": "02-09-2021"
  },
  {
    "days_to_complete": 998,
    "daily_series_completed_rolling": 2633,
    "date": "02-08-2021"
  },
  {
    "days_to_complete": 1037,
    "daily_series_completed_rolling": 2536,
    "date": "02-07-2021"
  },
  {
    "days_to_complete": 1042,
    "daily_series_completed_rolling": 2524,
    "date": "02-06-2021"
  },
  {
    "days_to_complete": 1085,
    "daily_series_completed_rolling": 2425,
    "date": "02-05-2021"
  },
  {
    "days_to_complete": 1281,
    "daily_series_completed_rolling": 2058,
    "date": "02-04-2021"
  },
  {
    "days_to_complete": 1365,
    "daily_series_completed_rolling": 1933,
    "date": "02-03-2021"
  },
  {
    "days_to_complete": 1409,
    "daily_series_completed_rolling": 1875,
    "date": "02-02-2021"
  },
  {
    "days_to_complete": 1466,
    "daily_series_completed_rolling": 1805,
    "date": "02-01-2021"
  },
  {
    "days_to_complete": 1439,
    "daily_series_completed_rolling": 1840,
    "date": "01-31-2021"
  },
  {
    "days_to_complete": 1477,
    "daily_series_completed_rolling": 1793,
    "date": "01-30-2021"
  },
  {
    "days_to_complete": 1590,
    "daily_series_completed_rolling": 1666,
    "date": "01-29-2021"
  },
  {
    "days_to_complete": 1667,
    "daily_series_completed_rolling": 1590,
    "date": "01-28-2021"
  },
  {
    "days_to_complete": 1707,
    "daily_series_completed_rolling": 1554,
    "date": "01-27-2021"
  },
  {
    "days_to_complete": 1704,
    "daily_series_completed_rolling": 1558,
    "date": "01-26-2021"
  },
  {
    "days_to_complete": 1848,
    "daily_series_completed_rolling": 1438,
    "date": "01-25-2021"
  },
  {
    "days_to_complete": 1973,
    "daily_series_completed_rolling": 1348,
    "date": "01-24-2021"
  },
  {
    "days_to_complete": 1913,
    "daily_series_completed_rolling": 1391,
    "date": "01-23-2021"
  },
  {
    "days_to_complete": 1902,
    "daily_series_completed_rolling": 1399,
    "date": "01-22-2021"
  },
  {
    "days_to_complete": 1975,
    "daily_series_completed_rolling": 1348,
    "date": "01-21-2021"
  },
  {
    "days_to_complete": 2167,
    "daily_series_completed_rolling": 1229,
    "date": "01-20-2021"
  },
  {
    "days_to_complete": 2225,
    "daily_series_completed_rolling": 1198,
    "date": "01-19-2021"
  },
  {
    "days_to_complete": 2031,
    "daily_series_completed_rolling": 1314,
    "date": "01-18-2021"
  },
  {
    "days_to_complete": 1635,
    "daily_series_completed_rolling": 1633,
    "date": "01-17-2021"
  },
  {
    "days_to_complete": 1585,
    "daily_series_completed_rolling": 1685,
    "date": "01-16-2021"
  },
  {
    "days_to_complete": 1335,
    "daily_series_completed_rolling": 2000,
    "date": "01-15-2021"
  },
  {
    "days_to_complete": 1003,
    "daily_series_completed_rolling": 2663,
    "date": "01-14-2021"
  },
  {
    "days_to_complete": 898,
    "daily_series_completed_rolling": 2976,
    "date": "01-13-2021"
  },
  {
    "days_to_complete": 979,
    "daily_series_completed_rolling": 2732,
    "date": "01-12-2021"
  },
  {
    "days_to_complete": 1146,
    "daily_series_completed_rolling": 2336,
    "date": "01-11-2021"
  },
  {
    "days_to_complete": 1463,
    "daily_series_completed_rolling": 1832,
    "date": "01-10-2021"
  },
  {
    "days_to_complete": 1556,
    "daily_series_completed_rolling": 1724,
    "date": "01-09-2021"
  },
  {
    "days_to_complete": 2011,
    "daily_series_completed_rolling": 1335,
    "date": "01-08-2021"
  },
  {
    "days_to_complete": 4453,
    "daily_series_completed_rolling": 604,
    "date": "01-07-2021"
  },
  {
    "days_to_complete": 15747,
    "daily_series_completed_rolling": 171,
    "date": "01-06-2021"
  },
  {
    "days_to_complete": 38478,
    "daily_series_completed_rolling": 70,
    "date": "01-05-2021"
  },
  {
    "days_to_complete": 81629,
    "daily_series_completed_rolling": 33,
    "date": "01-04-2021"
  },
  {
    "days_to_complete": 673486,
    "daily_series_completed_rolling": 4,
    "date": "01-03-2021"
  }
]